DairyBrainUtils/DairyBrainUtils.py
DairyBrainUtils/__init__.py
dairybrain-database-functions/__init__.py
dairybrain-database-functions/dairybrain-database-functions.py
DairyBrainUtils-0.3.8.dist-info/LICENSE
DairyBrainUtils-0.3.8.dist-info/METADATA
DairyBrainUtils-0.3.8.dist-info/WHEEL
DairyBrainUtils-0.3.8.dist-info/top_level.txt
DairyBrainUtils-0.3.8.dist-info/RECORD
