Metadata-Version: 2.1
Name: DairyBrainUtils
Version: 0.3.8
Summary: A set of functions that interacts with a database. It contains some basic functionalities along with some other Dairy-Brain-specific functionalities.
Home-page: https://github.com/DairyBrain/AgDH_DairyBrainUtils
Author: Rui Pan, Steve Wangen
Author-email: srwangen@wisc.edu
Classifier: Programming Language :: Python :: 3
Classifier: License :: OSI Approved :: MIT License
Classifier: Operating System :: OS Independent
Requires-Python: >=3.6
License-File: LICENSE
Requires-Dist: SQLAlchemy
Requires-Dist: sqlalchemy-utils
